ppgnss/__init__.py
ppgnss/gnss_ftp.py
ppgnss/gnss_geodesy.py
ppgnss/gnss_influx.py
ppgnss/gnss_io.py
ppgnss/gnss_iono.py
ppgnss/gnss_ntrip.py
ppgnss/gnss_rtcm.py
ppgnss/gnss_rtklib.py
ppgnss/gnss_time.py
ppgnss/gnss_trop.py
ppgnss/gnss_utils.py
ppgnss/ppget.py
ppgnss/ppsubnet.py
ppgnss/pptime.py
ppgnss/extend/__init__.py
ppgnss/extend/setup.py
ppgnss-1.7.22.dist-info/LICENSE
ppgnss-1.7.22.dist-info/METADATA
ppgnss-1.7.22.dist-info/WHEEL
ppgnss-1.7.22.dist-info/entry_points.txt
ppgnss-1.7.22.dist-info/top_level.txt
ppgnss-1.7.22.dist-info/RECORD
