Metadata-Version: 2.2
Name: ppgnss
Version: 1.7.22
Summary: Python Package of GNSS data processing
Home-page: https://gitee.com/snnugiser/ppgnss
Author: Liang Zhang
Author-email: lzhang2019@whu.edu.cn
License-File: LICENSE
Requires-Dist: numpy>=1.19.5
Requires-Dist: matplotlib>=3.3.3
Requires-Dist: pandas>=0.25.3
Requires-Dist: xarray>=0.16.2
Requires-Dist: wget>=3.2
Requires-Dist: h5py>=3.14.0
Dynamic: author
Dynamic: author-email
Dynamic: home-page
Dynamic: requires-dist
Dynamic: summary
